rmbclient/__init__.py
rmbclient/api.py
rmbclient/cli.py
rmbclient/exceptions.py
rmbclient/log.py
rmbclient/rmb.py
rmbclient/upload.py
rmbclient/models/__init__.py
rmbclient/models/base.py
rmbclient/models/chat.py
rmbclient/models/datasource.py
rmbclient/models/message.py
rmbclient/models/run.py
rmbcommon/__init__.py
rmbcommon/tools.py
rmbcommon/version.py
rmbcommon/exceptions/__init__.py
rmbcommon/exceptions/client.py
rmbcommon/exceptions/server.py
rmbcommon/exceptions/server_base.py
rmbcommon/exceptions/server_plugins.py
rmbcommon/models/__init__.py
rmbcommon/models/base.py
rmbcommon/models/bi.py
rmbcommon/models/chat.py
rmbcommon/models/datasource.py
rmbcommon/models/meta.py
rmb_client-0.11.12.dist-info/METADATA
rmb_client-0.11.12.dist-info/WHEEL
rmb_client-0.11.12.dist-info/entry_points.txt
rmb_client-0.11.12.dist-info/top_level.txt
rmb_client-0.11.12.dist-info/RECORD
