Metadata-Version: 2.1
Name: rmb-client
Version: 0.11.12
Summary: RMB SDK.
Home-page: https://github.com/DataMini/rmb
Author: lele
Requires-Dist: requests
Requires-Dist: tabulate
Requires-Dist: pybase62
